TtAnquanXinxianquanRenyuanCongyeZhinan/README.md
TtAnquanXinxianquanRenyuanCongyeZhinan/__init__.py
TtAnquanXinxianquanRenyuanCongyeZhinan/__main__.py
TtAnquanXinxianquanRenyuanCongyeZhinan/file.pdf
TtAnquanXinxianquanRenyuanCongyeZhinan/index.html
tt_anquan_xinxianquan_renyuan_congye_zhinan-2024.3.2.0.dist-info/METADATA
tt_anquan_xinxianquan_renyuan_congye_zhinan-2024.3.2.0.dist-info/WHEEL
tt_anquan_xinxianquan_renyuan_congye_zhinan-2024.3.2.0.dist-info/entry_points.txt
tt_anquan_xinxianquan_renyuan_congye_zhinan-2024.3.2.0.dist-info/top_level.txt
tt_anquan_xinxianquan_renyuan_congye_zhinan-2024.3.2.0.dist-info/RECORD
